Metadata-Version: 2.1
Name: PyCurlify
Version: 2.0.0
Summary: PyCurl: Un envoltorio flexible alrededor de la biblioteca requests para realizar solicitudes HTTP.
Home-page: https://github.com/CarrilloTlx/PyCurlify
Author: José Luis Coyotzi Ipatzi
Author-email: jlci811122@gmail.com
License: MIT
Classifier: Programming Language :: Python :: 3
Classifier: License :: OSI Approved :: MIT License
Classifier: Operating System :: OS Independent
Requires-Python: >=3.6
License-File: LICENSE.md
